PyRabbitmqRpc/__init__.py
PyRabbitmqRpc/client.py
PyRabbitmqRpc/conf.py
PyRabbitmqRpc/manager.py
PyRabbitmqRpc-1.2.1.dist-info/LICENSE.txt
PyRabbitmqRpc-1.2.1.dist-info/METADATA
PyRabbitmqRpc-1.2.1.dist-info/WHEEL
PyRabbitmqRpc-1.2.1.dist-info/top_level.txt
PyRabbitmqRpc-1.2.1.dist-info/RECORD
