Metadata-Version: 2.1
Name: PyRabbitmqRpc
Version: 1.2.1
Summary: This package mainly provides a solution for developers to implement RPC functionality using RabbitMQ.
Home-page: https://github.com/liu-xiaokai/PyRabbitmqRpc
Download-URL: https://github.com/liu-xiaokai/PyRabbitmqRpc/archive/refs/heads/main.zip
Author: NAIVEKAY
Author-email: genzhengmiaobuhong@163.com
License: MIT
Keywords: RPC,RABBITMQ,Python
Classifier: Development Status :: 3 - Alpha
Classifier: Intended Audience :: Developers
Classifier: Topic :: Software Development :: Build Tools
Classifier: License :: OSI Approved :: MIT License
Classifier: Programming Language :: Python :: 3
Classifier: Programming Language :: Python :: 3.4
Classifier: Programming Language :: Python :: 3.5
Classifier: Programming Language :: Python :: 3.6
License-File: LICENSE.txt
Requires-Dist: pika
